dictfunc/__init__.py
dictfunc/dictfunc.py
dictfunc-1.1.0.dist-info/LICENSE
dictfunc-1.1.0.dist-info/METADATA
dictfunc-1.1.0.dist-info/WHEEL
dictfunc-1.1.0.dist-info/top_level.txt
dictfunc-1.1.0.dist-info/RECORD
